<?xml version="1.0" encoding="UTF-8"?>
<?xml-model href="http://www.tei-c.org/release/xml/tei/custom/schema/relaxng/tei_all.rng" type="application/xml" schematypens="http://relaxng.org/ns/structure/1.0"?>
<?xml-model href="http://www.tei-c.org/release/xml/tei/custom/schema/relaxng/tei_all.rng" type="application/xml"
	schematypens="http://purl.oclc.org/dsdl/schematron"?>
<teiCorpus xmlns="http://www.tei-c.org/ns/1.0" xmlns:xi="http://www.w3.org/2001/XInclude">
   <teiHeader>
      <fileDesc>
         <titleStmt>
            <title>Mémoires d'Henri de Mesmes : édition critique numérique</title>
            <author><persName ref="https://isni.org/isni/0000000121402971"><nameLink>de</nameLink>
                  <surname>Mesmes</surname>, <forename>Henri</forename>
               </persName>(1532-1596)</author>
            <editor><persName ref="https://isni.org/isni/0000000504833613" xml:id="AV"
                     ><surname>Viaud</surname>,<forename>Alicia</forename>,</persName><persName><surname>Moulin</surname>,<forename>Chloé</forename></persName>,
                     <persName><surname>Brassard</surname>,<forename>Florence</forename></persName></editor>
            <funder/>
            <principal><persName ref="https://isni.org/isni/0000000504833613"
                     ><surname>Viaud</surname>,<forename>Alicia</forename></persName></principal>
         </titleStmt>
         <editionStmt>
            <edition/>
         </editionStmt>
         <publicationStmt>
            <p>Publication Information</p>
         </publicationStmt>
         <sourceDesc>
            <msDesc xml:lang="fr" type="composite">
               <msIdentifier>
                  <country>France</country>
                  <settlement>Paris</settlement>
                  <institution>Bibliothèque nationale de France</institution>
                  <repository>Département des manuscrits</repository>
                  <collection>Français</collection>
                  <idno>729</idno>
                  <altIdentifier>
                     <idno>Anc. 7162(3)</idno>
                  </altIdentifier>
                  <altIdentifier>
                     <idno>de Mesmes 546</idno>
                  </altIdentifier>
               </msIdentifier>
               <head>Henri de Mesmes, Opuscules et fragments</head>
               <msContents>
                  <summary/>
               </msContents>
               <physDesc>
                  <objectDesc>
                     <supportDesc>

                        <support>
                           <p><material/><locus/></p>
                        </support>
                        <extent><dimensions>
                              <height/>
                              <width/>
                           </dimensions></extent>
                        <foliation> </foliation>
                        <foliation/>
                        <collation/>
                        <condition/>
                     </supportDesc>
                     <layoutDesc>
                        <layout/>
                     </layoutDesc>
                     <!--                        layoutDesc - provisoire-->
                  </objectDesc>
                  <handDesc>
                     <handNote/>
                  </handDesc>
                  <!--                     handDesc provisoire-->
                  <bindingDesc>
                     <binding>
                        <condition/>
                     </binding>
                  </bindingDesc>
                  <!--                     bindingDesc provisoire-->
               </physDesc>
               <history/>
               <additional/>
               <msPart>
                  <msIdentifier>
                     <idno>729 ff. </idno>
                  </msIdentifier>
                  <msContents>
                     <msItemStruct>
                        <author/>
                        <respStmt>
                           <resp/>
                           <persName/>
                        </respStmt>
                        <title type="desc">Notes géographiques sur quelques lieux contestés des
                           Commentaires de César avec plan et carte</title>
                        <incipit/>
                        <explicit/>
                        <decoNote/>
                        <listBibl>
                           <bibl/>
                        </listBibl>
                        <filiation/>
                        <note/>
                        <textLang/>
                     </msItemStruct>
                  </msContents>
                  <physDesc/>
                  <history/>
               </msPart>
               <msPart>
                  <msIdentifier>
                     <idno>729 ff. </idno>
                  </msIdentifier>
                  <msContents>
                     <summary/>
                     <msItemStruct>
                        <author/>
                        <respStmt>
                           <resp/>
                           <persName/>
                        </respStmt>
                        <title type="main">De l'oraison de Xénophon sur les louanges
                           d'Agésilas</title>
                        <incipit/>
                        <explicit/>
                        <decoNote/>
                        <listBibl>
                           <bibl/>
                        </listBibl>
                        <filiation/>
                        <note/>
                        <textLang/>
                     </msItemStruct>
                  </msContents>
                  <physDesc/>
                  <history/>
               </msPart>
               <msPart>
                  <msIdentifier>
                     <idno>729 ff. </idno>
                  </msIdentifier>
                  <msContents>
                     <summary/>
                     <msItemStruct>
                        <author/>
                        <respStmt>
                           <resp/>
                           <persName/>
                        </respStmt>
                        <title type="desc">Traduction de divers passages de Plutarque sur les
                           éclipses de lune et de soleil</title>
                        <incipit/>
                        <explicit/>
                        <decoNote/>
                        <listBibl>
                           <bibl/>
                        </listBibl>
                        <filiation/>
                        <note/>
                        <textLang/>
                     </msItemStruct>
                  </msContents>
                  <physDesc/>
                  <history/>
               </msPart>
               <msPart>
                  <msIdentifier>
                     <idno>729 ff. 17r-33r</idno>
                  </msIdentifier>
                  <msContents>
                     <summary/>
                     <msItemStruct>
                        <author/>
                        <respStmt>
                           <resp/>
                           <persName/>
                        </respStmt>
                        <title type="desc">Manuscrit autographe des Mémoires</title>
                        <incipit/>
                        <explicit/>
                        <decoNote/>
                        <listBibl>
                           <bibl/>
                        </listBibl>
                        <filiation/>
                        <note/>
                        <textLang mainLang="frm" otherLangs="la"/>
                     </msItemStruct>
                  </msContents>
                  <physDesc/>
                  <history/>
               </msPart>
               <msPart>
                  <msIdentifier>
                     <idno>729 ff. </idno>
                  </msIdentifier>
                  <msContents>
                     <summary/>
                     <msItemStruct>
                        <author/>
                        <respStmt>
                           <resp/>
                           <persName/>
                        </respStmt>
                        <title type="desc">Fragments</title>
                        <incipit/>
                        <explicit/>
                        <decoNote/>
                        <listBibl>
                           <bibl/>
                        </listBibl>
                        <filiation/>
                        <note/>
                        <textLang/>
                     </msItemStruct>
                  </msContents>
                  <physDesc/>
                  <history/>
               </msPart>
               <msPart>
                  <msIdentifier>
                     <idno>729 ff. </idno>
                  </msIdentifier>
                  <msContents>
                     <summary/>
                     <msItemStruct>
                        <author/>
                        <respStmt>
                           <resp/>
                           <persName/>
                        </respStmt>
                        <title type="desc">Discours sur la mort de monsieur le président de
                           Marsan</title>
                        <incipit/>
                        <explicit/>
                        <decoNote/>
                        <listBibl>
                           <bibl/>
                        </listBibl>
                        <filiation/>
                        <note/>
                        <textLang/>
                     </msItemStruct>
                  </msContents>
                  <physDesc/>
                  <history/>
               </msPart>
               <msPart>
                  <msIdentifier>
                     <idno>729 ff. </idno>
                  </msIdentifier>
                  <msContents>
                     <summary/>
                     <msItemStruct>
                        <author/>
                        <respStmt>
                           <resp/>
                           <persName/>
                        </respStmt>
                        <title type="desc">Discours pieux en latin</title>
                        <incipit/>
                        <explicit/>
                        <decoNote/>
                        <listBibl>
                           <bibl/>
                        </listBibl>
                        <filiation/>
                        <note/>
                        <textLang/>
                     </msItemStruct>
                  </msContents>
                  <physDesc/>
                  <history/>
               </msPart>
            </msDesc>
         </sourceDesc>
      </fileDesc>
      <encodingDesc>
         <charDecl>
            <glyph xml:id="pro_glyph"/>
         </charDecl>
      </encodingDesc>
      <profileDesc>
         <creation>
            <listChange>
               <listChange>
                  <change target="#ny_histoire #certes_soymesmes">L'emplacement de l'ajout à la
                     phrase 3 (« Certes mieulx vaudroit avoir esté bien maistre de soymesmes »),
                     dans la marge de gauche, suggère qu'il est ultérieur à l'ajout de la phrase 4
                     (« ny ma ꝑfession les a produits dignes de grande histoire »).</change>
               </listChange>
            </listChange>
         </creation>
         <langUsage>
            <language ident="frm"/>
            <language ident="la"/>
         </langUsage>
      </profileDesc>
   </teiHeader>
   <TEI xmlns="http://www.tei-c.org/ns/1.0">
      <teiHeader>
         <fileDesc>
            <titleStmt>
               <title>f17ro</title>
            </titleStmt>
            <publicationStmt>
               <p>Publication Information</p>
            </publicationStmt>
            <sourceDesc>
               <msDesc>
                  <msIdentifier>
                     <institution>Bibliothèque nationale de France</institution>
                     <idno>Français 729</idno>
                  </msIdentifier>
               </msDesc>
            </sourceDesc>
         </fileDesc>
      </teiHeader>
      <facsimile>
         <surface>
            <graphic
               url="https://gallica.bnf.fr/iiif/ark:/12148/btv1b525191290/f39/full/full/0/native.jpg"
            />
         </surface>
      </facsimile>
      <xi:include href="1_f17r/f17rop1.xml"/>
      <xi:include href="1_f17r/f17rop2.xml"/>
      <xi:include href="1_f17r/f17rop3.xml"/>
      <xi:include href="1_f17r/f17rop4.xml"/>
      <xi:include href="1_f17r/f17rop5.xml"/>
      <xi:include href="1_f17r/f17rop6.xml"/>
   </TEI>
   <TEI xmlns="http://www.tei-c.org/ns/1.0">
      <teiHeader>
         <fileDesc>
            <titleStmt>
               <title>f17vo</title>
            </titleStmt>
            <publicationStmt>
               <p>Publication Information</p>
            </publicationStmt>
            <sourceDesc>
               <msDesc>
                  <msIdentifier>
                     <institution>Bibliothèque nationale de France</institution>
                     <idno>Français 729</idno>
                  </msIdentifier>
               </msDesc>
            </sourceDesc>
         </fileDesc>
      </teiHeader>
      <facsimile>
         <surface>
            <graphic
               url="https://gallica.bnf.fr/iiif/ark:/12148/btv1b525191290/f40/full/full/0/native.jpg"
            />
         </surface>
      </facsimile>
      <xi:include href="2_f17v/f17vop1.xml"/>
      <xi:include href="2_f17v/f17vop2.xml"/>
      <xi:include href="2_f17v/f17vop3.xml"/>
      <xi:include href="2_f17v/f17vop4.xml"/>
      <xi:include href="2_f17v/f17vop5.xml"/>
   </TEI>
   <TEI xmlns="http://www.tei-c.org/ns/1.0">
      <teiHeader>
         <fileDesc>
            <titleStmt>
               <title>f18ro</title>
            </titleStmt>
            <publicationStmt>
               <p>Publication Information</p>
            </publicationStmt>
            <sourceDesc>
               <msDesc>
                  <msIdentifier>
                     <institution>Bibliothèque nationale de France</institution>
                     <idno>Français 729</idno>
                  </msIdentifier>
               </msDesc>
            </sourceDesc>
         </fileDesc>
      </teiHeader>
      <facsimile>
         <surface>
            <graphic
               url="https://gallica.bnf.fr/iiif/ark:/12148/btv1b525191290/f41/full/full/0/native.jpg"
            />
         </surface>
      </facsimile>
      <xi:include href="3_f18r/f18rop1.xml"/>
      <xi:include href="3_f18r/f18rop2.xml"/>
      <xi:include href="3_f18r/f18rop3.xml"/>
      <xi:include href="3_f18r/f18rop4.xml"/>
      <xi:include href="3_f18r/f18rop5.xml"/>
      <xi:include href="3_f18r/f18rop6.xml"/>
      <xi:include href="3_f18r/f18rop7.xml"/>
      <xi:include href="3_f18r/f18rop8.xml"/>
      <xi:include href="3_f18r/f18rop9.xml"/>
   </TEI>
   <TEI xmlns="http://www.tei-c.org/ns/1.0">
      <teiHeader>
         <fileDesc>
            <titleStmt>
               <title>f18vo</title>
            </titleStmt>
            <publicationStmt>
               <p>Publication Information</p>
            </publicationStmt>
            <sourceDesc>
               <msDesc>
                  <msIdentifier>
                     <institution>Bibliothèque nationale de France</institution>
                     <idno>Français 729</idno>
                  </msIdentifier>
               </msDesc>
            </sourceDesc>
         </fileDesc>
      </teiHeader>
      <facsimile>
         <surface>
            <graphic
               url="https://gallica.bnf.fr/iiif/ark:/12148/btv1b525191290/f42/full/full/0/native.jpg"
            />
         </surface>
      </facsimile>
      <xi:include href="4_f18v/f18vop1.xml"/>
      <xi:include href="4_f18v/f18vop2.xml"/>
      <xi:include href="4_f18v/f18vop3.xml"/>
      <xi:include href="4_f18v/f18vop4.xml"/>
      <xi:include href="4_f18v/f18vop5.xml"/>
      <xi:include href="4_f18v/f18vop6.xml"/>
      <xi:include href="4_f18v/f18vop7.xml"/>
      <xi:include href="4_f18v/f18vop8.xml"/>
   </TEI>
   <TEI xmlns="http://www.tei-c.org/ns/1.0">
      <teiHeader>
         <fileDesc>
            <titleStmt>
               <title>f19ro</title>
            </titleStmt>
            <publicationStmt>
               <p>Publication Information</p>
            </publicationStmt>
            <sourceDesc>
               <msDesc>
                  <msIdentifier>
                     <institution>Bibliothèque nationale de France</institution>
                     <idno>Français 729</idno>
                  </msIdentifier>
               </msDesc>
            </sourceDesc>
         </fileDesc>
      </teiHeader>
      <facsimile>
         <surface>
            <graphic
               url="https://gallica.bnf.fr/iiif/ark:/12148/btv1b525191290/f43/full/full/0/native.jpg"
            />
         </surface>
      </facsimile>
      <xi:include href="5_f19r/f19rop1.xml"/>
      <xi:include href="5_f19r/f19rop2.xml"/>
      <xi:include href="5_f19r/f19rop3.xml"/>
      <xi:include href="5_f19r/f19rop4.xml"/>
      <xi:include href="5_f19r/f19rop5-6.xml"/>
      <xi:include href="5_f19r/f19rop7.xml"/>
      <xi:include href="5_f19r/f19rop8.xml"/>
      <xi:include href="5_f19r/f19rop9.xml"/>
   </TEI>
   <TEI xmlns="http://www.tei-c.org/ns/1.0">
      <teiHeader>
         <fileDesc>
            <titleStmt>
               <title>f19vo</title>
            </titleStmt>
            <publicationStmt>
               <p>Publication Information</p>
            </publicationStmt>
            <sourceDesc>
               <msDesc>
                  <msIdentifier>
                     <institution>Bibliothèque nationale de France</institution>
                     <idno>Français 729</idno>
                  </msIdentifier>
               </msDesc>
            </sourceDesc>
         </fileDesc>
      </teiHeader>
      <facsimile>
         <surface>
            <graphic
               url="https://gallica.bnf.fr/iiif/ark:/12148/btv1b525191290/f44/full/full/0/native.jpg"
            />
         </surface>
      </facsimile>
      <xi:include href="6_f19v/f19vop1.xml"/>
      <xi:include href="6_f19v/f19vop2-3.xml"/>
      <xi:include href="6_f19v/f19vop4.xml"/>
      <xi:include href="6_f19v/f19vop5.xml"/>
      <xi:include href="6_f19v/f19vop6.xml"/>
      <xi:include href="6_f19v/f19vop7.xml"/>
      <xi:include href="6_f19v/f19vop8.xml"/>
      <xi:include href="6_f19v/f19vop9.xml"/>
      <xi:include href="6_f19v/f19vop10.xml"/>
      <xi:include href="6_f19v/f19vop11.xml"/>
      <xi:include href="6_f19v/f19vop12.xml"/>
   </TEI>
   <TEI xmlns="http://www.tei-c.org/ns/1.0">
      <teiHeader>
         <fileDesc>
            <titleStmt>
               <title>f20ro</title>
            </titleStmt>
            <publicationStmt>
               <p>Publication Information</p>
            </publicationStmt>
            <sourceDesc>
               <msDesc>
                  <msIdentifier>
                     <institution>Bibliothèque nationale de France</institution>
                     <idno>Français 729</idno>
                  </msIdentifier>
               </msDesc>
            </sourceDesc>
         </fileDesc>
      </teiHeader>
      <facsimile>
         <surface>
            <graphic
               url="https://gallica.bnf.fr/iiif/ark:/12148/btv1b525191290/f45/full/full/0/native.jpg"
            />
         </surface>
      </facsimile>
      <xi:include href="7_f20r/f20rop1.xml"/>
      <xi:include href="7_f20r/f20rop2.xml"/>
      <xi:include href="7_f20r/f20rop3.xml"/>
   </TEI>
   <TEI xmlns="http://www.tei-c.org/ns/1.0">
      <teiHeader>
         <fileDesc>
            <titleStmt>
               <title>f20vo</title>
            </titleStmt>
            <publicationStmt>
               <p>Publication Information</p>
            </publicationStmt>
            <sourceDesc>
               <msDesc>
                  <msIdentifier>
                     <institution>Bibliothèque nationale de France</institution>
                     <idno>Français 729</idno>
                  </msIdentifier>
               </msDesc>
            </sourceDesc>
         </fileDesc>
      </teiHeader>
      <facsimile>
         <surface>
            <graphic
               url="https://gallica.bnf.fr/iiif/ark:/12148/btv1b525191290/f46/full/full/0/native.jpg"
            />
            <graphic
               url="https://gallica.bnf.fr/iiif/ark:/12148/btv1b525191290/f47/267,311,3490,2182/full/0/default.jpg"
            />
         </surface>
      </facsimile>
      <xi:include href="8_f20v/f20vop1.xml"/>
      <xi:include href="8_f20v/f20vop2.xml"/>
      <xi:include href="8_f20v/f20vop3.xml"/>
      <xi:include href="8_f20v/f20vop4.xml"/>
   </TEI>
   <TEI xmlns="http://www.tei-c.org/ns/1.0">
      <teiHeader>
         <fileDesc>
            <titleStmt>
               <title>f21ro</title>
            </titleStmt>
            <publicationStmt>
               <p>Publication Information</p>
            </publicationStmt>
            <sourceDesc>
               <msDesc>
                  <msIdentifier>
                     <institution>Bibliothèque nationale de France</institution>
                     <idno>Français 729</idno>
                  </msIdentifier>
               </msDesc>
            </sourceDesc>
         </fileDesc>
      </teiHeader>
      <facsimile>
         <surface>
            <graphic
               url="https://gallica.bnf.fr/iiif/ark:/12148/btv1b525191290/f47/full/full/0/native.jpg"
            />
         </surface>
      </facsimile>
      <xi:include href="9_f21r/f21rop1-2.xml"/>
      <xi:include href="9_f21r/f21rop3.xml"/>
      <xi:include href="9_f21r/f21rop4.xml"/>
      <xi:include href="9_f21r/f21rop5.xml"/>
      <xi:include href="9_f21r/f21rop6.xml"/>
   </TEI>
   <TEI xmlns="http://www.tei-c.org/ns/1.0">
      <teiHeader>
         <fileDesc>
            <titleStmt>
               <title>f26vo</title>
            </titleStmt>
            <publicationStmt>
               <p>Publication Information</p>
            </publicationStmt>
            <sourceDesc>
               <msDesc>
                  <msIdentifier>
                     <institution>Bibliothèque nationale de France</institution>
                     <idno>Français 729</idno>
                  </msIdentifier>
               </msDesc>
            </sourceDesc>
         </fileDesc>
      </teiHeader>
      <facsimile>
         <surface>
            <graphic
               url="https://gallica.bnf.fr/iiif/ark:/12148/btv1b525191290/f58/full/full/0/native.jpg"
            />
         </surface>
      </facsimile>
      <xi:include href="20_f26v/f26vop1-8.xml"/>
      <xi:include href="20_f26v/f26vop9.xml"/>
      <xi:include href="20_f26v/f26vop10.xml"/>
      <xi:include href="20_f26v/f26vop11.xml"/>
      <xi:include href="20_f26v/f26vop12.xml"/>
      <xi:include href="20_f26v/f26vop13.xml"/>
      <xi:include href="20_f26v/f26vop14.xml"/>
      <xi:include href="20_f26v/f26vop15.xml"/>
      <xi:include href="20_f26v/f26vop16.xml"/>
      <xi:include href="20_f26v/f26vop17.xml"/>
   </TEI>
</teiCorpus>
